

        {"web":{"client_id":"197222315244-0kp4vqo945g6mksrvqn734ab5c6rsoh4.apps.googleusercontent.com",
            "project_id":"all-in-mentoring",
            "auth_uri":"https://accounts.google.com/o/oauth2/auth",
            "token_uri":"https://oauth2.googleapis.com/token",
            "auth_provider_x509_cert_url":"https://www.googleapis.com/oauth2/v1/certs",
            "client_secret":"d5TNeKs-OS-yWU5ksapfqWdU",
            "redirect_uris":["http://alliin.org"],
            "javascript_origins":["http://alliin.org"]}}